psycopg_pool_prometheus/__init__.py
psycopg_pool_prometheus/py.typed
psycopg_pool_prometheus-0.0.1.dist-info/LICENSE
psycopg_pool_prometheus-0.0.1.dist-info/METADATA
psycopg_pool_prometheus-0.0.1.dist-info/WHEEL
psycopg_pool_prometheus-0.0.1.dist-info/top_level.txt
psycopg_pool_prometheus-0.0.1.dist-info/RECORD
